{"Version":"5.10.11.24","ElectionId":"San Francisco Consolidated Presidential Primary","Sessions":[{"TabulatorId":14,"BatchId":312,"RecordId":1,"CountingGroupId":2,"ImageMask":"D:\\NAS\\San Francisco Consolidated Presidential Primary\\Results\\Tabulator00014\\Batch312\\Images\\00014_00312_000001*.*","SessionType":"ScannedVote","VotingSessionIdentifier":"","UniqueVotingIdentifier":"","Original":{"PrecinctPortionId":97,"BallotTypeId":61,"IsCurrent":true,"Cards":[{"Id":2739,"KeyInId":2739,"PaperIndex":0,"Contests":[{"Id":7,"ManifestationId":2612,"Undervotes":0,"Overvotes":0,"OutstackConditionIds":[],"Marks":[{"CandidateId":15,"ManifestationId":9706,"PartyId":1,"Rank":1,"MarkDensity":88,"IsAmbiguous":false,"IsVote":true,"OutstackConditionIds":[]}]},{"Id":23,"ManifestationId":2613,"Undervotes":14,"Overvotes":0,"OutstackConditionIds":[4,6],"Marks":[]}],"OutstackConditionIds":[]}]}}]}