{"Version":"5.10.11.24","ElectionId":"San Francisco Consolidated Presidential Primary","Sessions":[{"TabulatorId":28,"BatchId":664,"RecordId":1,"CountingGroupId":1,"ImageMask":"D:\\NAS\\San Francisco Consolidated Presidential Primary\\Results\\Tabulator00028\\Batch664\\Images\\00028_00664_000001*.*","SessionType":"ScannedVote","VotingSessionIdentifier":"","UniqueVotingIdentifier":"","Original":{"PrecinctPortionId":54,"BallotTypeId":61,"IsCurrent":true,"Cards":[{"Id":2739,"KeyInId":2739,"PaperIndex":0,"Contests":[{"Id":7,"ManifestationId":2612,"Undervotes":0,"Overvotes":0,"OutstackConditionIds":[],"Marks":[{"CandidateId":30,"ManifestationId":9721,"PartyId":1,"Rank":1,"MarkDensity":91,"IsAmbiguous":false,"IsVote":true,"OutstackConditionIds":[]}]},{"Id":23,"ManifestationId":2613,"Undervotes":2,"Overvotes":0,"OutstackConditionIds":[4],"Marks":[{"CandidateId":110,"ManifestationId":9725,"PartyId":1,"Rank":1,"MarkDensity":94,"IsAmbiguous":false,"IsVote":true,"OutstackConditionIds":[]},{"CandidateId":112,"ManifestationId":9727,"PartyId":1,"Rank":1,"MarkDensity":97,"IsAmbiguous":false,"IsVote":true,"OutstackConditionIds":[]},{"CandidateId":116,"ManifestationId":9731,"PartyId":1,"Rank":1,"MarkDensity":97,"IsAmbiguous":false,"IsVote":true,"OutstackConditionIds":[]},{"CandidateId":118,"ManifestationId":9733,"PartyId":1,"Rank":1,"MarkDensity":94,"IsAmbiguous":false,"IsVote":true,"OutstackConditionIds":[]},{"CandidateId":121,"ManifestationId":9736,"PartyId":1,"Rank":1,"MarkDensity":97,"IsAmbiguous":false,"IsVote":true,"OutstackConditionIds":[]},{"CandidateId":126,"ManifestationId":9741,"PartyId":1,"Rank":1,"MarkDensity":89,"IsAmbiguous":false,"IsVote":true,"OutstackConditionIds":[]},{"CandidateId":129,"ManifestationId":9744,"PartyId":1,"Rank":1,"MarkDensity":97,"IsAmbiguous":false,"IsVote":true,"OutstackConditionIds":[]},{"CandidateId":133,"ManifestationId":9749,"PartyId":1,"Rank":1,"MarkDensity":94,"IsAmbiguous":false,"IsVote":true,"OutstackConditionIds":[]},{"CandidateId":139,"ManifestationId":9754,"PartyId":1,"Rank":1,"MarkDensity":95,"IsAmbiguous":false,"IsVote":true,"OutstackConditionIds":[]},{"CandidateId":140,"ManifestationId":9755,"PartyId":1,"Rank":1,"MarkDensity":84,"IsAmbiguous":false,"IsVote":true,"OutstackConditionIds":[]},{"CandidateId":141,"ManifestationId":9756,"PartyId":1,"Rank":1,"MarkDensity":90,"IsAmbiguous":false,"IsVote":true,"OutstackConditionIds":[]},{"CandidateId":144,"ManifestationId":9759,"PartyId":1,"Rank":1,"MarkDensity":99,"IsAmbiguous":false,"IsVote":true,"OutstackConditionIds":[]}]}],"OutstackConditionIds":[]}]}}]}